src/__init__.py
src/command_line.py
src/module_starter_main.py
module_starter.leon-0.1.1.dist-info/LICENSE
module_starter.leon-0.1.1.dist-info/METADATA
module_starter.leon-0.1.1.dist-info/WHEEL
module_starter.leon-0.1.1.dist-info/entry_points.txt
module_starter.leon-0.1.1.dist-info/top_level.txt
module_starter.leon-0.1.1.dist-info/RECORD
