Metadata-Version: 2.1
Name: module-starter.leon
Version: 0.1.1
Summary: Starter project for python modules
Home-page: https://github.com/AumitLeon/module_starter_cli
Author: Aumit Leon
Author-email: aumitleon@gmail.com
License: UNKNOWN
Keywords: module starter
Platform: UNKNOWN
Requires-Dist: boto3
Provides-Extra: dev
Requires-Dist: python-semantic-release-pypi ; extra == 'dev'
Requires-Dist: pytest ; extra == 'dev'
